{
    "abstract": "This work was supported by Jack Ma Foundation to KK, AWC and AW, the Clifford Craig Foundation to KLF and KK, NHMRC Leadership Investigator Grant to KK (1173871), NHMRC Program Grant to KK (1071916), NHMRC Program Grant to DLD (#1132975), NHMRC program grant to SJK (#1149990), Research Grants Council of the Hong Kong Special Administrative Region, China (#T11-712/19-N) to KK. AWC is supported by a NHMRC Career Development Fellowship (#1140509), KK by NHMRC Senior Research Fellowship (1102792), DLD by a NHMRC Principal Research Fellowship (#1137285). SJK by NHMRC Senior Principal Research Fellowship (#1136322). CES has received funding from the European Union\u0092s Horizon 2020 research and innovation program under the Marie Sk\u0142odowska-Curie grant agreement No 792532. LH is supported by the Melbourne International Research Scholarship (MIRS) and the Melbourne International Fee Remission Scholarship (MIFRS) from The University of Melbourne. JAJ is supported by an NHMRC Early Career Fellowship (ECF) (APP1123673)",
    "affiliations": [
        "The University of Melbourne. JAJ is supported by an NHMRC Early Career Fellowship (ECF) (APP1123673)"
    ],
    "author": "Brendon Y. Chua; Bruce Wines; Katherine Kedzierska; Luca Hensen; Florian Krammer; Chinn Yi Wong; Melissa M. Lemke; Adam K. Wheatley; Kelly B. Arnold; Katie L. Flanagan; Paul Young; Hannah G. Kelly; Keith Chappell; Kevin J. Selva; Robyn Esterbauer; Carolien E. van de Sandt; Fatima Amanat; Daniel Watterson; David C. Jackson; Denise L. Doolan; Jennifer A. Juno; Jane Crowe; Marios Koutsakos; Thi H.O. Nguyen; Christina Y. Lee; Amy W. Chung; Allen C. Cheng; Naphak Modhiran; P. Mark Hogarth; Stephen J. Kent; Louise C. Rowntree; Suzanne K. Shoffner; Hyon-Xhi Tan",
    "date": 2020,
    "doi": "10.1101/2020.05.11.20098459",
    "identifiers": {
        "url": "http://medrxiv.org/cgi/content/short/2020.05.11.20098459"
    },
    "title": "Distinct systems serology features in children, elderly and COVID patients",
    "funding": [
        {
            "award-group": [
                {
                    "funding-source": "Jack Ma Foundation"
                },
                {
                    "funding-source": "AWC and AW,"
                },
                {
                    "funding-source": "Clifford Craig Foundation"
                },
                {
                    "funding-source": "KLF and KK, NHMRC"
                },
                {
                    "funding-source": "Leadership Investigator Grant",
                    "award-id": [
                        "1173871"
                    ]
                },
                {
                    "funding-source": "NHMRC Program Grant",
                    "award-id": [
                        "1071916"
                    ]
                },
                {
                    "funding-source": "NHMRC Program Grant",
                    "award-id": [
                        "#1132975"
                    ]
                },
                {
                    "funding-source": "NHMRC",
                    "award-id": [
                        "#1149990"
                    ]
                },
                {
                    "funding-source": "Research Grants Council of the Hong Kong Special Administrative Region, China",
                    "award-id": [
                        "#T11-712/19-N"
                    ]
                }
            ],
            "funding-statement": "This work was supported by Jack Ma Foundation to KK, AWC and AW, the Clifford Craig Foundation to KLF and KK, NHMRC Leadership Investigator Grant to KK (1173871), NHMRC Program Grant to KK (1071916), NHMRC Program Grant to DLD (#1132975), NHMRC program grant to SJK (#1149990), Research Grants Council of the Hong Kong Special Administrative Region, China (#T11-712/19-N) to KK"
        },
        {
            "award-group": [
                {
                    "funding-source": "NHMRC Career Development Fellowship",
                    "award-id": [
                        "#1140509"
                    ]
                },
                {
                    "funding-source": "NHMRC Senior Research Fellowship",
                    "award-id": [
                        "1102792"
                    ]
                },
                {
                    "funding-source": "NHMRC Principal Research Fellowship",
                    "award-id": [
                        "#1137285"
                    ]
                }
            ],
            "funding-statement": "AWC is supported by a NHMRC Career Development Fellowship (#1140509), KK by NHMRC Senior Research Fellowship (1102792), DLD by a NHMRC Principal Research Fellowship (#1137285)"
        },
        {
            "award-group": [
                {
                    "funding-source": "European Union\u0092s Horizon"
                },
                {
                    "funding-source": "Marie Sk\u0142odowska-Curie",
                    "award-id": [
                        "792532"
                    ]
                }
            ],
            "funding-statement": "CES has received funding from the European Union\u0092s Horizon 2020 research and innovation program under the Marie Sk\u0142odowska-Curie grant agreement No 792532"
        },
        {
            "award-group": [
                {
                    "funding-source": "Melbourne International Research Scholarship"
                },
                {
                    "funding-source": "Melbourne International Fee Remission Scholarship"
                },
                {
                    "funding-source": "The University of Melbourne"
                }
            ],
            "funding-statement": "LH is supported by the Melbourne International Research Scholarship (MIRS) and the Melbourne International Fee Remission Scholarship (MIFRS) from The University of Melbourne"
        },
        {
            "award-group": [
                {
                    "funding-source": "NHMRC Early Career Fellowship",
                    "award-id": [
                        "APP1123673"
                    ]
                }
            ],
            "funding-statement": "JAJ is supported by an NHMRC Early Career Fellowship (ECF) (APP1123673)"
        }
    ]
}